{
  "name": "shai-typescript",
  "displayName": "SHAI TypeScript",
  "description": "TypeScript-specific conventions and workflows. Install alongside shai-core for any TS project.",
  "version": "0.1.0",
  "publisher": "kirillshilin",
  "license": "MIT",
  "keywords": [
    "typescript",
    "tsconfig",
    "testing",
    "jest",
    "vitest"
  ],
  "instructions": [
    "instructions/shai-tsconfig.instructions.md",
    "instructions/shai-typescript-testing.instructions.md",
    "instructions/shai-typescript.instructions.md",
    "instructions/shai-zod-schema.instructions.md"
  ],
  "skills": [
    "skills/shai-scaffold-ts-workspace",
    "skills/shai-unit-testing-ts"
  ],
  "agents": [],
  "hooks": []
}
